cilantropy/__init__.py
cilantropy/__main__.py
cilantropy/cilantropy.py
cilantropy/console.py
cilantropy/dist_worker.py
cilantropy/helpers.py
cilantropy/metadata.py
cilantropy/settings.py
cilantropy/write_plist.py
cilantropy/static/about.png
cilantropy/static/box-icon.png
cilantropy/static/box.png
cilantropy/static/cilantropy_icon.png
cilantropy/static/contribute.png
cilantropy/static/down-arrow.png
cilantropy/static/favicon.ico
cilantropy/static/info.png
cilantropy/static/left-arrow.png
cilantropy/static/loader.gif
cilantropy/static/mail.png
cilantropy/static/refresh-icon.png
cilantropy/static/terminal-icon.png
cilantropy/static/world.png
cilantropy/static/css/an-old-hope.css
cilantropy/static/css/extra.css
cilantropy/static/css/jquery-ui.min.css
cilantropy/static/css/images/ui-icons_444444_256x240.png
cilantropy/static/css/images/ui-icons_555555_256x240.png
cilantropy/static/css/images/ui-icons_777620_256x240.png
cilantropy/static/css/images/ui-icons_777777_256x240.png
cilantropy/static/css/images/ui-icons_cc0000_256x240.png
cilantropy/static/css/images/ui-icons_ffffff_256x240.png
cilantropy/static/js/ajax-queue.js
cilantropy/static/js/highlight.pack.js
cilantropy/static/js/jquery-ui.min.js
cilantropy/static/js/main.js
cilantropy/templates/about.html
cilantropy/templates/console_scripts.html
cilantropy/templates/distribution.html
cilantropy/templates/main.html
cilantropy/templates/metadata.html
cilantropy/templates/metadata10.html
cilantropy/templates/metadata11.html
cilantropy/templates/metadata12.html
cilantropy/templates/metadata21.html
cilantropy/templates/paste_pkg_template.html
cilantropy/templates/pypi_update.html
cilantropy/templates/pypi_upgrade.html
cilantropy/templates/system_information.html
cilantropy/tests/test_main.py
cilantropy/tests/test_metadata.py
cilantropy-0.2.7.post1.dist-info/entry_points.txt
cilantropy-0.2.7.post1.dist-info/LICENSE
cilantropy-0.2.7.post1.dist-info/WHEEL
cilantropy-0.2.7.post1.dist-info/METADATA
cilantropy-0.2.7.post1.dist-info/RECORD
