Metadata-Version: 2.1
Name: cilantropy
Version: 0.2.7.post1
Summary: Cilantropy is a Python Package Manager interface created to provide an "easy-to-use" visual and also a command-line interface for Pythonistas.
Home-page: https://github.com/foozzi/cilantropy
License: UNKNOWN
Keywords: package manager,distribution tool,cilantropy
Author: Tkachenko Igor
Author-email: foozzione@gmail.com
Requires-Python: >=3
Classifier: Development Status :: 4 - Beta
Classifier: Environment :: Web Environment
Classifier: License :: OSI Approved :: BSD License
Classifier: Operating System :: OS Independent
Classifier: Programming Language :: Python
Classifier: Topic :: Internet :: WWW/HTTP :: Dynamic Content
Classifier: Topic :: Software Development :: Libraries :: Python Modules
Requires-Dist: Flask>=1.1.2
Requires-Dist: colorama>=0.4.3
Requires-Dist: docopt>=0.6.2
Requires-Dist: docutils>=0.16
Requires-Dist: jinja2>=2.11.2
Requires-Dist: flit>=2,<4 ; extra == "dev"
Requires-Dist: pytest ; extra == "test"
Requires-Dist: uWSGI>=2.0.19.1 ; extra == "uwsgi"
Project-URL: Download, https://github.com/foozzi/cilantropy/archive/0.2.7.tar.gz
Provides-Extra: dev
Provides-Extra: test
Provides-Extra: uwsgi
